LICENSE
README-pypi.md
README.md
pyproject.toml
CheckAMG/__init__.py
CheckAMG/__main__.py
CheckAMG/files/AMG_filters.tsv
CheckAMG/files/AMGs.tsv
CheckAMG/files/APG_filters.tsv
CheckAMG/files/APGs.tsv
CheckAMG/files/AReG_filters.tsv
CheckAMG/files/AReGs.tsv
CheckAMG/files/FOAM.tsv
CheckAMG/files/hmm_id_to_name.tsv
CheckAMG/files/lgbm_feature_names.joblib
CheckAMG/files/lgbm_model.joblib
CheckAMG/files/lgbm_thresholds.joblib
CheckAMG/files/mobile_genes.tsv
CheckAMG/files/viral_hallmark_genes.tsv
CheckAMG/files/vscores.tsv
CheckAMG/scripts/CheckAMG_annotate.py
CheckAMG/scripts/CheckAMG_annotate.smk
CheckAMG/scripts/add_annots.py
CheckAMG/scripts/annotate_hmm.py
CheckAMG/scripts/checkAMG_ASCII.py
CheckAMG/scripts/check_circular.py
CheckAMG/scripts/curate_annots.py
CheckAMG/scripts/download_dbs.py
CheckAMG/scripts/filter_by_cds.py
CheckAMG/scripts/filter_by_length.py
CheckAMG/scripts/genome_context.py
CheckAMG/scripts/load_prot_paths.py
CheckAMG/scripts/make_final_table.py
CheckAMG/scripts/map_protein_data.py
CheckAMG/scripts/organize_proteins.py
CheckAMG/scripts/run_pyrodigal.py
checkamg.egg-info/PKG-INFO
checkamg.egg-info/SOURCES.txt
checkamg.egg-info/dependency_links.txt
checkamg.egg-info/entry_points.txt
checkamg.egg-info/requires.txt
checkamg.egg-info/top_level.txt